libbencode/__init__.py
libbencode/decoder.py
libbencode/encoder.py
libbencode/exceptions.py
libbencode/version.py
libbencode-1.0.2.dist-info/METADATA
libbencode-1.0.2.dist-info/WHEEL
libbencode-1.0.2.dist-info/RECORD
