Metadata-Version: 2.3
Name: libbencode
Version: 1.0.2
Summary: Bencode encoder and decoder.
Project-URL: Repository, https://github.com/zrekryu/libbencode
Project-URL: Issues, https://github.com/zrekryu/libbencode/issues
Author-email: Zrekryu <zrekryu@gmail.com>
Keywords: bencode,bittorrent,torrent
Classifier: Development Status :: 5 - Production/Stable
Classifier: Intended Audience :: Developers
Classifier: License :: OSI Approved :: MIT License
Classifier: Operating System :: OS Independent
Classifier: Programming Language :: Python
Classifier: Programming Language :: Python :: 3.11
Classifier: Programming Language :: Python :: 3.12
Classifier: Topic :: Software Development :: Libraries :: Python Modules
Classifier: Topic :: Utilities
Requires-Python: >=3.11
